Workbook

Sheet Instrucciones
B1: JLIZ BUSINESS · LEVANTAMIENTO DE INFORMACIÓN DEL NEGOCIO
B3: Para qué sirve esta planilla | C3: Antes de programar el inventario, las compras y las ventas, necesitamos entender cómo funciona el negocio de verdad: cómo se pesa, cómo se cobra, qué se pierde y qué reglas hay que respetar. Cada respuesta se traduce en una configuración concreta del sistema.
B4: Cómo se llena | C4: Responda solo en las celdas amarillas. No hay respuestas incorrectas: si algo no aplica, escriba 'no aplica'. Si no está seguro, escriba lo que cree y agregue 'por confirmar'. Es mejor un dato aproximado que una celda vacía.
B5: Qué es urgente | C5: Las preguntas marcadas 'bloqueante' detienen el desarrollo de la fase indicada: sin ellas hay que adivinar, y adivinar en inventario y precios se paga caro después. Parta por esas.
B6: Las tres hojas de datos | C6: Al final hay tres hojas para cargar productos, clientes y proveedores REALES. Con eso el sistema arranca con su información y no con datos de ejemplo. Si ya tiene un Excel con esto, no lo copie: envíelo tal como está.
B7: Cuánto demora | C7: Las hojas A a G se responden en una conversación de 45 a 60 minutos. Las hojas de datos se pueden llenar después, con calma o pasando el Excel que ya usa.
B9: AVANCE DE LA PLANILLA
B10: Sección | C10: Preguntas | D10: Respondidas | E10: Avance | F10: Contenido
B11: A. Negocio | C11: =COUNTA('A. Negocio'!$F$6:$F$120) | D11: =COUNTA('A. Negocio'!$E$6:$E$120) | E11: =IFERROR(D11/C11,0) | F11: La empresa, sus horarios, su tamaño y sus problemas de hoy
B12: B. Productos y precios | C12: =COUNTA('B. Productos y precios'!$F$6:$F$120) | D12: =COUNTA('B. Productos y precios'!$E$6:$E$120) | E12: =IFERROR(D12/C12,0) | F12: Unidades, presentaciones, procesamiento, listas de precios y stock mínimo
B13: C. Compras | C13: =COUNTA('C. Compras'!$F$6:$F$120) | D13: =COUNTA('C. Compras'!$E$6:$E$120) | E13: =IFERROR(D13/C13,0) | F13: Proveedores, recepción, flete y costo real por kilo
B14: D. Clientes y ventas | C14: =COUNTA('D. Clientes y ventas'!$F$6:$F$120) | D14: =COUNTA('D. Clientes y ventas'!$E$6:$E$120) | E14: =IFERROR(D14/C14,0) | F14: Cartera, toma de pedidos y la regla del peso facturado
B15: E. Preparación y reparto | C15: =COUNTA('E. Preparación y reparto'!$F$6:$F$120) | D15: =COUNTA('E. Preparación y reparto'!$E$6:$E$120) | E15: =IFERROR(D15/C15,0) | F15: Empaque, pesaje, rutas, cobro en terreno y evidencia de entrega
B16: F. Dinero | C16: =COUNTA('F. Dinero'!$F$6:$F$120) | D16: =COUNTA('F. Dinero'!$E$6:$E$120) | E16: =IFERROR(D16/C16,0) | F16: Formas de pago, crédito, cobranza, documentos tributarios y margen
B17: G. Mermas y reglas | C17: =COUNTA('G. Mermas y reglas'!$F$6:$F$120) | D17: =COUNTA('G. Mermas y reglas'!$E$6:$E$120) | E17: =IFERROR(D17/C17,0) | F17: Pérdidas, excepciones, permisos y alertas automáticas
B18: TOTAL | C18: =SUM(C11:C17) | D18: =SUM(D11:D17) | E18: =IFERROR(D18/C18,0)
B20: LEYENDA
B21: Celda amarilla | C21: Aquí escribe usted
B22: Fila gris en las hojas de datos | C22: Ejemplo de referencia: no la borre ni la modifique
B23: Prioridad 'bloqueante' | C23: Sin esta respuesta no se puede avanzar con esa fase
B25: Documento preparado para el levantamiento de requerimientos del sistema JLIZ Business · Las respuestas se consolidan en docs/ARQUITECTURA.md antes de comenzar la Fase 2.

Sheet A. Negocio
A1: A · EL NEGOCIO Y SU OPERACIÓN
A2: Contexto general. Estas respuestas configuran los datos de la empresa, los horarios de corte y el tamaño real de la operación.
A4: N° | B4: Pregunta | C4: Por qué importa / qué define en el sistema | D4: Ejemplo de respuesta | E4: SU RESPUESTA | F4: Prioridad
A5: Identificación de la empresa
A6: A1 | B6: Razón social completa y nombre de fantasía | C6: Encabezado de documentos y configuración del sistema | D6: Distribuidora JLIZ Ltda. / JLIZ Pescados | F6: Fase 2 · bloqueante
A7: A2 | B7: RUT de la empresa | C7: Documentos y futura facturación electrónica | D7: 76.123.456-7 | F7: Fase 2 · bloqueante
A8: A3 | B8: Dirección, comuna y región de la bodega principal | C8: Origen de las rutas de reparto | D8: Av. Lo Espejo 0200, Lo Espejo, RM | F8: Fase 2 · bloqueante
A9: A4 | B9: Teléfono, WhatsApp y correo del negocio | C9: Contacto en documentos y avisos | D9: +56 9 1234 5678 / contacto@jliz.cl | F9: Fase 2
A10: A5 | B10: ¿Tiene más de un local, bodega o punto de venta? | C10: Define si hay que manejar ubicaciones o sucursales separadas | D10: Solo una bodega con 3 cámaras | F10: Fase 2 · bloqueante
A12: Ritmo de la operación
A13: A6 | B13: ¿A qué hora llega la mercadería y a qué hora sale el reparto? | C13: Define el horario de corte de pedidos y las alertas del día | D13: Llega 05:00, reparto sale 08:30 | F13: Fase 3
A14: A7 | B14: ¿Hasta qué hora recibe pedidos para despachar al día siguiente? | C14: Corte automático de pedidos y aviso a los clientes | D14: Hasta las 19:00 del día anterior | F14: Fase 3
A15: A8 | B15: ¿Cuántos pedidos atiende en un día normal? ¿Y en el día más cargado del año? | C15: Dimensiona el tablero de pedidos y el rendimiento necesario | D15: 25 normales, 90 en Semana Santa | F15: Fase 3
A16: A9 | B16: ¿Cuántos kilos mueve al mes aproximadamente? | C16: Dimensiona inventario y reportes | D16: 18.000 kg | F16: Fase 2
A17: A10 | B17: ¿Qué días de la semana opera? ¿Hay temporadas altas y bajas? | C17: Reportes comparativos y proyección de demanda | D17: Lunes a sábado. Peak: Semana Santa, 18 y fin de año | F17: Fase 5
A18: A11 | B18: ¿Cómo se llaman las cámaras o zonas de almacenamiento? Nómbrelas todas | C18: Cada lote se guarda con su ubicación real | D18: Cámara fresco 1, Cámara congelado, Antesala | F18: Fase 2 · bloqueante
A20: Cómo se trabaja hoy
A21: A12 | B21: ¿Con qué lleva hoy el control? (cuaderno, Excel, WhatsApp, otro sistema) | C21: Define qué se migra y qué hábitos hay que respetar | D21: Cuaderno + Excel de precios + WhatsApp | F21: Fase 2 · bloqueante
A22: A13 | B22: Si usa un sistema o Excel, ¿puede enviarnos una copia? | C22: Permite cargar el catálogo y los clientes reales de una vez | D22: Sí, planilla de precios y lista de clientes | F22: Fase 2 · bloqueante
A23: A14 | B23: ¿Cuáles son hoy los 3 problemas que más plata o tiempo le cuestan? | C23: Define qué se prioriza en las siguientes fases | D23: No sé cuánto stock tengo; me equivoco al cobrar; no sé quién me debe | F23: Fase 2 · bloqueante
A24: A15 | B24: ¿Qué información necesita ver sí o sí todas las mañanas? | C24: Define el tablero principal | D24: Qué tengo que despachar hoy y cuánto stock queda | F24: Fase 2
A25: A16 | B25: ¿Cuántos celulares/tablets hay disponibles para el personal? ¿Android o iPhone? | C25: Define el diseño de la interfaz de terreno | D25: 3 Android en bodega, repartidores usan el suyo | F25: Fase 4
A26: A17 | B26: ¿Hay señal de internet en bodega y en las rutas de reparto? | C26: Define si se necesita trabajo sin conexión (offline) | D26: En bodega sí, en ruta a veces se corta | F26: Fase 7
A27: A18 | B27: ¿Qué balanza usan? ¿Tiene salida de datos o imprime etiqueta? | C27: Define si el peso se puede capturar automáticamente | D27: Balanza digital 300 kg sin conexión | F27: Fase 4
A28: A19 | B28: ¿Tiene impresora térmica o de etiquetas? ¿Qué tamaño? | C28: Define impresión de comprobantes y etiquetas de bulto | D28: No / Sí, 80 mm | F28: Fase 6

Sheet B. Productos y precios
A1: B · PRODUCTOS, UNIDADES Y PRECIOS
A2: El corazón del sistema. Cómo se mide, se presenta y se cobra cada producto.
A4: N° | B4: Pregunta | C4: Por qué importa / qué define en el sistema | D4: Ejemplo de respuesta | E4: SU RESPUESTA | F4: Prioridad
A5: Cómo se mide y se vende
A6: B1 | B6: ¿Todo se vende por kilo, o hay productos por unidad, caja o bandeja? | C6: Define la unidad base de cada producto y todos los cálculos de stock | D6: Pescado por kilo; choritos por malla de 10 kg; ostiones por bandeja | F6: Fase 2 · bloqueante
A7: B2 | B7: Cuando vende una caja o malla, ¿siempre pesa lo mismo o varía? | C7: Define si la caja es unidad fija o se convierte a kilos variables | D7: La malla dice 10 kg pero llega entre 9,5 y 10,5 | F7: Fase 2 · bloqueante
A8: B3 | B8: ¿Qué presentaciones maneja del mismo pescado? (entero, HG, filete, medallón, trozado) | C8: Cada presentación es un producto distinto con su propio stock y precio | D8: Salmón: entero, filete c/piel, filete s/piel | F8: Fase 2 · bloqueante
A9: B4 | B9: ¿Compra entero y procesa en el local (filetea, limpia, trocea)? | C9: Determina si hay que construir el módulo de transformación (un lote entra, otro sale) | D9: Sí, compramos merluza entera y fileteamos | F9: Fase 2 · bloqueante
A10: B5 | B10: Si procesa: ¿cuánto rinde? Ej: 100 kg de entero dan ¿cuántos kg de filete? | C10: Es el cálculo de costo real del producto procesado y de la merma de proceso | D10: 100 kg entero → 45 kg filete + 55 kg desecho | F10: Fase 2 · bloqueante
A11: B6 | B11: ¿Vende algo que no sea pescado o marisco? (hielo, envases, abarrotes) | C11: Define categorías adicionales del catálogo | D11: Vendemos hielo en bolsa | F11: Fase 2
A13: Precios
A14: B7 | B14: ¿Los precios que maneja son con IVA incluido o netos? | C14: Afecta TODOS los totales del sistema. Es la decisión más importante de esta hoja | D14: Netos, el IVA se agrega en la factura | F14: Fase 2 · bloqueante
A15: B8 | B15: ¿Cada cuánto cambia el precio de venta? ¿Quién lo define? | C15: Define si se necesita precio por día y bitácora de cambios de precio | D15: Semanal, lo define el dueño según lo que costó | F15: Fase 2 · bloqueante
A16: B9 | B16: ¿Qué listas de precios usa realmente? Nómbrelas | C16: Se crean las listas y se asignan a cada cliente | D16: Público, Restaurante, Mayorista | F16: Fase 2 · bloqueante
A17: B10 | B17: ¿Hace descuento por volumen? ¿Desde cuántos kilos y de cuánto? | C17: Define reglas automáticas de precio | D17: Sobre 100 kg, 5% menos | F17: Fase 3
A18: B11 | B18: ¿Se negocia precio caso a caso con algunos clientes? | C18: Define si el vendedor puede editar el precio y si requiere autorización | D18: Sí, con 3 clientes grandes | F18: Fase 3
A19: B12 | B19: ¿Redondea los precios? ¿A cuánto? | C19: Formato de precios en el sistema | D19: Siempre a la centena: $8.900 | F19: Fase 2
A21: Control de stock por producto
A22: B13 | B22: ¿Qué productos nunca pueden faltar? ¿Cuál es el mínimo de cada uno? | C22: Configura las alertas automáticas de stock bajo | D22: Merluza nunca bajo 50 kg | F22: Fase 2 · bloqueante
A23: B14 | B23: ¿Cuántos días dura cada tipo de producto en cámara? | C23: Configura vencimientos y el orden de salida (lo más antiguo primero) | D23: Fresco 3 días, congelado 6 meses | F23: Fase 2 · bloqueante
A24: B15 | B24: ¿Usa códigos internos o SKU para los productos? | C24: Se respetan sus códigos en vez de inventar otros | D24: SAL-01, MER-02 | F24: Fase 2
A25: B16 | B25: ¿Quiere foto de cada producto en el sistema? | C25: Define si se habilita almacenamiento de imágenes | D25: Sí, ayuda al personal nuevo | F25: Fase 2

Sheet C. Compras
A1: C · PROVEEDORES, COMPRAS Y RECEPCIÓN
A2: Cómo entra la mercadería y cómo se calcula lo que realmente costó cada kilo.
A4: N° | B4: Pregunta | C4: Por qué importa / qué define en el sistema | D4: Ejemplo de respuesta | E4: SU RESPUESTA | F4: Prioridad
A5: Proveedores
A6: C1 | B6: ¿A cuántos proveedores le compra habitualmente? | C6: Dimensiona el módulo y el comparador de precios | D6: 3 fijos y 2 ocasionales | F6: Fase 2 · bloqueante
A7: C2 | B7: ¿Le compra a pescadores, caletas o particulares sin factura? | C7: Define si se necesita registro de compra sin documento tributario | D7: Sí, a veces en caleta con boleta de compra | F7: Fase 2
A8: C3 | B8: ¿Cómo se acuerda el precio? ¿Fijo, del día, por WhatsApp? | C8: Define si hay que guardar precio pactado por compra | D8: Precio del día por WhatsApp cada mañana | F8: Fase 2 · bloqueante
A9: C4 | B9: ¿Le compra a crédito? ¿A cuántos días paga cada proveedor? | C9: Configura las cuentas por pagar | D9: Chiloé a 15 días, el resto contado | F9: Fase 5
A10: C5 | B10: ¿Da anticipos o paga por adelantado? | C10: Define manejo de anticipos a proveedor | D10: Sí, 50% al pedir | F10: Fase 5
A12: Recepción de la mercadería
A13: C6 | B13: ¿Quién recibe y pesa la mercadería que llega? | C13: Define el rol y la responsabilidad en la trazabilidad | D13: El jefe de bodega | F13: Fase 2 · bloqueante
A14: C7 | B14: ¿El peso que llega coincide con el de la guía o factura? ¿Cuánta diferencia es normal? | C14: Define el registro de diferencia de peso en recepción | D14: Casi siempre llega 1 o 2 kg menos | F14: Fase 2 · bloqueante
A15: C8 | B15: ¿Paga flete aparte? ¿Camión propio o de terceros? ¿Cuánto cuesta en promedio? | C15: El flete se prorratea al costo por kilo de cada producto | D15: Flete externo, $45.000 por viaje | F15: Fase 2 · bloqueante
A16: C9 | B16: ¿Qué otros costos tiene una compra? (hielo, cajas, comisiones, peajes) | C16: Se suman al costo real del kilo | D16: Hielo $12.000 por viaje | F16: Fase 2 · bloqueante
A17: C10 | B17: ¿Qué datos DEBE quedar registrados de cada recepción? | C17: Define los campos obligatorios del lote | D17: Origen, fecha de captura, temperatura, proveedor | F17: Fase 2 · bloqueante
A18: C11 | B18: ¿Mide y registra temperatura al recibir? | C18: Define si se agrega control de cadena de frío | D18: Sí, con termómetro de punzón | F18: Fase 6
A19: C12 | B19: ¿Qué hace si el producto llega en mal estado o falta? | C19: Define devoluciones a proveedor y notas de crédito | D19: Se descuenta de la factura | F19: Fase 2
A20: C13 | B20: ¿Sernapesca u otra autoridad le exige algún registro de trazabilidad? | C20: Puede obligar a guardar datos y a emitir reportes específicos | D20: Sí, guardamos las guías por 2 años | F20: Fase 2 · bloqueante
A21: C14 | B21: ¿Quién autoriza una compra grande? | C21: Define si se requiere aprobación en el sistema | D21: Solo el dueño sobre $2.000.000 | F21: Fase 5

Sheet D. Clientes y ventas
A1: D · CLIENTES Y VENTAS
A2: Cómo llega un pedido, cómo se cotiza y cómo se cobra realmente.
A4: N° | B4: Pregunta | C4: Por qué importa / qué define en el sistema | D4: Ejemplo de respuesta | E4: SU RESPUESTA | F4: Prioridad
A5: Los clientes
A6: D1 | B6: ¿Cuántos clientes activos tiene hoy? ¿Cuántos compran cada semana? | C6: Dimensiona el CRM y los reportes de frecuencia | D6: 45 activos, 20 semanales | F6: Fase 3 · bloqueante
A7: D2 | B7: ¿Qué tipos de cliente atiende y en qué proporción de sus ventas? | C7: Define listas de precios y segmentación de reportes | D7: 70% restaurantes, 20% mayorista, 10% público | F7: Fase 3 · bloqueante
A8: D3 | B8: ¿Un cliente puede tener varias direcciones de entrega? | C8: Define el manejo de direcciones múltiples | D8: Sí, cadena con 3 locales | F8: Fase 3 · bloqueante
A9: D4 | B9: ¿Quién hace el pedido es la misma persona que paga? | C9: Define contactos separados por cliente | D9: Pide el chef, paga administración | F9: Fase 3
A10: D5 | B10: ¿Hay clientes con los que trabaja con precio fijo por contrato? | C10: Define listas de precios especiales por cliente | D10: Sí, un hotel con precio fijo mensual | F10: Fase 3
A12: Cómo se toma el pedido
A13: D6 | B13: ¿Por dónde le llegan los pedidos? ¿En qué proporción? | C13: Define si se necesita entrada rápida de pedidos o portal de cliente | D13: 80% WhatsApp, 20% teléfono | F13: Fase 3 · bloqueante
A14: D7 | B14: ¿El cliente pide kilos exactos o cantidades aproximadas? | C14: Define cómo se maneja la diferencia entre lo pedido y lo entregado | D14: Pide 'unos 15 kilos de salmón' | F14: Fase 3 · bloqueante
A15: D8 | B15: ¿Hay clientes con pedido fijo y repetido cada semana? | C15: Permite plantillas de pedido recurrente | D15: Sí, 8 restaurantes piden lo mismo cada martes | F15: Fase 3
A16: D9 | B16: ¿Se puede vender algo que todavía no ha llegado a bodega? | C16: Define si se permite vender contra compra futura (stock negativo controlado) | D16: Sí, se compromete y se compra mañana | F16: Fase 3 · bloqueante
A18: La regla más importante: el peso
A19: D10 | B19: ¿Le cobra al cliente el peso que pidió o el peso real que despachó? | C19: Es la regla central del sistema de facturación. Hoy está configurado para cobrar el peso real | D19: El peso real que sale de la balanza | F19: Fase 3 · bloqueante
A20: D11 | B20: ¿Cuánta diferencia de peso acepta sin avisar al cliente? | C20: Define alertas al preparar (ej. si difiere más de 5%, avisar) | D20: Hasta 5% para arriba o para abajo | F20: Fase 4 · bloqueante
A21: D12 | B21: Si falta producto al preparar, ¿qué se hace? | C21: Define el comportamiento cuando el stock no alcanza | D21: Se despacha menos y se avisa por WhatsApp | F21: Fase 4 · bloqueante
A22: D13 | B22: ¿Cobra el despacho? ¿Desde qué monto es gratis? | C22: Configura el cargo de transporte automático | D22: $15.000 bajo 50 kg, gratis sobre eso | F22: Fase 3
A23: D14 | B23: ¿Acepta devoluciones? ¿En qué casos y qué se hace con el producto? | C23: Define el flujo de devolución y su impacto en inventario | D23: Solo si viene en mal estado, se da nota de crédito | F23: Fase 5

Sheet E. Preparación y reparto
A1: E · PREPARACIÓN, EMPAQUE Y REPARTO
A2: Lo que hace el equipo en bodega y en la calle. Define las pantallas móviles de los trabajadores.
A4: N° | B4: Pregunta | C4: Por qué importa / qué define en el sistema | D4: Ejemplo de respuesta | E4: SU RESPUESTA | F4: Prioridad
A5: Preparación y empaque
A6: E1 | B6: ¿Quién prepara los pedidos y en qué horario? | C6: Define los turnos y las tareas asignadas por rol | D6: 2 personas de 06:00 a 09:00 | F6: Fase 4 · bloqueante
A7: E2 | B7: ¿Se prepara pedido por pedido, o se pesa todo un producto y luego se reparte? | C7: Cambia por completo el diseño de la pantalla de empaque | D7: Pedido por pedido | F7: Fase 4 · bloqueante
A8: E3 | B8: ¿Se pesa cada producto de cada pedido y se anota? | C8: Define el registro de peso real por línea | D8: Sí, se anota en la hoja del pedido | F8: Fase 4 · bloqueante
A9: E4 | B9: ¿Se etiquetan los bultos? ¿Qué información lleva la etiqueta? | C9: Define impresión de etiquetas y contenido | D9: Nombre del cliente y producto, a mano | F9: Fase 6
A10: E5 | B10: ¿Cuántos bultos o cajas salen por pedido en promedio? | C10: Define el conteo de bultos en la entrega | D10: 2 a 4 cajas | F10: Fase 4
A11: E6 | B11: ¿Se agrega hielo? ¿Se cobra o se descuenta del peso? | C11: Puede afectar el peso facturado | D11: Hielo gratis, no se pesa | F11: Fase 4 · bloqueante
A12: E7 | B12: ¿Quién revisa que el pedido esté completo antes de salir? | C12: Define si hay un paso de control de calidad antes del despacho | D12: El jefe de bodega revisa | F12: Fase 4
A14: Reparto
A15: E8 | B15: ¿Cuántos vehículos y repartidores tiene? ¿Propios o externos? | C15: Define usuarios de reparto y asignación de rutas | D15: 2 camionetas propias, 1 externo en peak | F15: Fase 4 · bloqueante
A16: E9 | B16: ¿Cuántas rutas hace al día? ¿Las zonas son fijas? | C16: Define el armado de rutas | D16: 2 rutas: norte y sur | F16: Fase 4 · bloqueante
A17: E10 | B17: ¿Quién arma la ruta y con qué criterio? | C17: Define si el orden lo pone el administrador o el repartidor | D17: El dueño, por cercanía | F17: Fase 4
A18: E11 | B18: ¿El repartidor cobra en la entrega? ¿En efectivo, transferencia o ambas? | C18: Define el cobro en terreno y la rendición de caja | D18: Sí, efectivo y transferencia al momento | F18: Fase 4 · bloqueante
A19: E12 | B19: ¿El repartidor puede vender producto extra en la calle? | C19: Define si necesita venta desde el vehículo con su propio stock | D19: A veces vende lo que sobra | F19: Fase 4 · bloqueante
A20: E13 | B20: ¿Hoy pide firma, foto o algún respaldo de entrega? | C20: Define la evidencia obligatoria al entregar | D20: Firma en la guía impresa | F20: Fase 4 · bloqueante
A21: E14 | B21: ¿Qué pasa si el cliente no está o rechaza el pedido? | C21: Define el flujo de entrega fallida y el retorno a bodega | D21: Se devuelve y se reprograma | F21: Fase 4 · bloqueante
A22: E15 | B22: ¿Entrega documento impreso con el pedido? ¿Cuál? | C22: Define qué documento debe generar el sistema | D22: Guía de despacho impresa | F22: Fase 5
A23: E16 | B23: ¿Hay horario comprometido de entrega con algún cliente? | C23: Define ventanas horarias y alertas de atraso | D23: Restaurantes antes de las 11:00 | F23: Fase 4

Sheet F. Dinero
A1: F · PAGOS, COBRANZA Y RENTABILIDAD
A2: Cómo entra la plata, a quién se le fía y cómo se sabe si el negocio está ganando.
A4: N° | B4: Pregunta | C4: Por qué importa / qué define en el sistema | D4: Ejemplo de respuesta | E4: SU RESPUESTA | F4: Prioridad
A5: Cobro y pagos
A6: F1 | B6: ¿Qué formas de pago recibe y en qué proporción? | C6: Configura los métodos de pago del sistema | D6: 60% transferencia, 30% efectivo, 10% crédito | F6: Fase 5 · bloqueante
A7: F2 | B7: ¿A qué clientes les fía y a cuántos días? | C7: Configura el crédito y las cuentas por cobrar | D7: Restaurantes a 30 días, hoteles a 45 | F7: Fase 5 · bloqueante
A8: F3 | B8: ¿Tiene un límite de crédito por cliente? ¿Quién lo autoriza? | C8: Bloqueo automático de pedidos a clientes sobre su límite | D8: Sí, $2.000.000. Lo autorizo yo | F8: Fase 5 · bloqueante
A9: F4 | B9: ¿A partir de cuántos días considera que una deuda está vencida? | C9: Define las alertas de cobranza | D9: A los 30 días de la factura | F9: Fase 5 · bloqueante
A10: F5 | B10: ¿Cobra interés o recargo por atraso? | C10: Define el cálculo de mora | D10: No | F10: Fase 5
A11: F6 | B11: ¿Quién hace la cobranza y cómo la lleva hoy? | C11: Define el tablero de cobranza y sus responsables | D11: Yo mismo, por WhatsApp | F11: Fase 5
A13: Documentos tributarios
A14: F7 | B14: ¿Emite boleta, factura y/o guía de despacho? | C14: Define qué documentos debe generar el sistema | D14: Factura y guía de despacho | F14: Fase 5 · bloqueante
A15: F8 | B15: ¿Con qué sistema factura hoy? (Nubox, Bsale, SII gratuito, otro) | C15: Define la integración futura de facturación electrónica | D15: Facturación gratuita del SII | F15: Fase 5 · bloqueante
A16: F9 | B16: ¿Quiere que el sistema EMITA la factura, o solo que registre el número? | C16: Es la diferencia entre integrar con el SII o solo controlar | D16: Por ahora solo registrar el número | F16: Fase 5 · bloqueante
A18: Rentabilidad
A19: F10 | B19: ¿Sabe hoy cuánto gana por kilo o por cliente? | C19: Define qué reportes de margen se construyen primero | D19: No, solo estimo | F19: Fase 5
A20: F11 | B20: ¿Qué costos fijos mensuales tiene? (arriendo, sueldos, luz, camión) | C20: Permite calcular margen neto, no solo bruto | D20: $4.500.000 mensuales | F20: Fase 5
A21: F12 | B21: ¿Paga comisiones o bonos por venta, kilo o entrega? | C21: Define cálculos de comisión por trabajador | D21: Repartidor gana bono por entrega | F21: Fase 5
A22: F13 | B22: ¿Quién puede ver los costos y los márgenes? | C22: Define permisos: hoy solo el administrador los ve | D22: Solo yo | F22: Fase 5 · bloqueante
A23: F14 | B23: ¿Qué informes le pide su contador y con qué frecuencia? | C23: Define los reportes exportables | D23: Ventas mensuales y compras con IVA | F23: Fase 5

Sheet G. Mermas y reglas
A1: G · MERMAS, CALIDAD Y REGLAS DEL NEGOCIO
A2: Las pérdidas reales y las reglas que el sistema debe hacer cumplir (o permitir).
A4: N° | B4: Pregunta | C4: Por qué importa / qué define en el sistema | D4: Ejemplo de respuesta | E4: SU RESPUESTA | F4: Prioridad
A5: Mermas y pérdidas
A6: G1 | B6: ¿Cuánto se pierde al mes aproximadamente? ¿En kilos o en pesos? | C6: Define la línea base para medir la mejora | D6: Unos 200 kg al mes | F6: Fase 2 · bloqueante
A7: G2 | B7: ¿Cuáles son las causas más comunes de pérdida? | C7: Configura los motivos de merma del sistema | D7: Se pasa de fecha, se maltrata, diferencia de peso | F7: Fase 2 · bloqueante
A8: G3 | B8: El producto pierde peso solo en cámara (deshidratación). ¿Cuánto estima? | C8: Define ajustes periódicos de inventario | D8: 1% a 2% por día | F8: Fase 2 · bloqueante
A9: G4 | B9: ¿Qué hace con el producto que no se vendió a tiempo? | C9: Define si hay cambio de estado, rebaja o baja del producto | D9: Se congela o se vende más barato | F9: Fase 2 · bloqueante
A10: G5 | B10: ¿Registra hoy las pérdidas en algún lado? | C10: Define el punto de partida del módulo de mermas | D10: No | F10: Fase 2
A11: G6 | B11: ¿Quién puede dar de baja producto? | C11: Define permisos y autorizaciones para mermas | D11: Solo el jefe de bodega y yo | F11: Fase 2 · bloqueante
A13: Reglas y excepciones
A14: G7 | B14: ¿Alguna vez vendió más de lo que tenía? ¿Cómo lo resolvieron? | C14: Define si el sistema bloquea o solo advierte | D14: Sí, se compró de urgencia a otro proveedor | F14: Fase 3 · bloqueante
A15: G8 | B15: ¿Quién puede cambiar un precio de venta? | C15: Define permisos y bitácora de cambios de precio | D15: Solo yo | F15: Fase 3 · bloqueante
A16: G9 | B16: ¿Quién puede anular o modificar un pedido ya despachado? | C16: Hoy el sistema lo impide. Define si debe haber una excepción con autorización | D16: Solo yo, y debe quedar registrado | F16: Fase 3 · bloqueante
A17: G10 | B17: ¿Un descuento sobre cierto porcentaje debe ser autorizado? | C17: Define el flujo de aprobación de descuentos | D17: Sobre 10% me tienen que preguntar | F17: Fase 3
A18: G11 | B18: ¿Hay información que ciertos trabajadores NO deben ver nunca? | C18: Ajusta la matriz de permisos | D18: Los repartidores no ven costos ni márgenes | F18: Fase 2 · bloqueante
A19: G12 | B19: ¿Qué error del personal le ha costado más caro? | C19: Define qué validaciones agregar primero | D19: Despachar al cliente equivocado | F19: Fase 4
A20: G13 | B20: Si el sistema pudiera avisarle 3 cosas automáticamente, ¿cuáles serían? | C20: Define las notificaciones automáticas | D20: Stock bajo, cliente que debe, pedido sin despachar | F20: Fase 6 · bloqueante
A21: G14 | B21: ¿Qué le gustaría dejar de hacer a mano mañana mismo? | C21: Prioriza el desarrollo | D21: Sumar los pedidos con calculadora | F21: Fase 2

Sheet Datos · Productos
A1: DATOS REALES · CATÁLOGO DE PRODUCTOS
A2: Liste TODOS los productos que vende, uno por fila. Si el mismo pescado se vende en dos presentaciones (entero y filete), van en dos filas distintas. La fila gris es solo un ejemplo: no la borre, escriba desde la fila 6.
A4: Nombre del producto | B4: Especie | C4: Presentación | D4: Categoría | E4: Unidad de venta (kg / unidad / caja) | F4: Código interno (SKU) | G4: Stock mínimo | H4: Precio público | I4: Precio restaurante | J4: Precio mayorista | K4: Precio distribuidor | L4: Costo aprox. de compra | M4: Días que dura | N4: Proveedor habitual | O4: Observaciones
A5: Salmón filete sin piel | B5: Salmón | C5: Filete sin piel | D5: Procesado | E5: kg | F5: SAL-FIL | G5: 25 | H5: 16900 | I5: 15500 | J5: 14500 | K5: 13500 | L5: 14100 | M5: 4 | N5: Pesquera Chiloé | O5: El más vendido a restaurantes

Sheet Datos · Clientes
A1: DATOS REALES · CLIENTES
A2: Liste sus clientes activos. Con esto el sistema arranca con su cartera real y su historial de precios y crédito.
A4: Nombre / Local | B4: Empresa (razón social) | C4: RUT | D4: Tipo de cliente | E4: Persona de contacto | F4: Teléfono | G4: WhatsApp | H4: Correo | I4: Dirección de entrega | J4: Comuna | K4: Lista de precios | L4: Días de crédito | M4: Límite de crédito | N4: Observaciones
A5: Restaurante Mar Azul | B5: Mar Azul SpA | C5: 76.222.111-3 | D5: Restaurante | E5: Carla Muñoz | F5: +56 9 9111 2233 | G5: +56991112233 | H5: compras@marazul.cl | I5: Av. Providencia 2410 | J5: Providencia | K5: Restaurante | L5: 30 | M5: 2000000 | N5: Recibe solo antes de las 11:00

Sheet Datos · Proveedores
A1: DATOS REALES · PROVEEDORES
A2: Liste sus proveedores habituales. Esto permite comparar precios entre ellos y calcular el costo real de cada kilo.
A4: Nombre | B4: Empresa | C4: RUT | D4: Persona de contacto | E4: Teléfono | F4: WhatsApp | G4: Correo | H4: Dirección | I4: Comuna / Origen | J4: Qué productos le vende | K4: Días de pago | L4: Evaluación (1 a 5) | M4: Observaciones
A5: Pesquera Chiloé | B5: Pesquera Chiloé Ltda. | C5: 76.543.210-9 | D5: Marcos Uribe | E5: +56 9 8123 4567 | F5: +56981234567 | G5: ventas@pescachiloe.cl | H5: Ruta 5 Sur km 1100 | I5: Castro | J5: Salmón, congrio, choritos | K5: 15 | L5: 5 | M5: Llega los martes y viernes a las 05:00
